Metadata-Version: 2.1
Name: gender-render
Version: 1.0.0.post0
Summary: Template-system and proof-of-concept for rendering gender-neutral text- and email-templates with the correct pronouns of all people involved.
Home-page: https://github.com/phseiff/gender-render/
Author: phseiff
Author-email: phseiff@phseiff.com
License: MIT (limited to python-files that are actually part of the package installation, which excludes data sets and documentation/specifications that come with the software; refer to the `LICENSE-implementation.txt`-file that comes with this version of the software on PyPi for the full definition of what is covered by this license and what is not.)
Platform: UNKNOWN
Classifier: Programming Language :: Python :: 3
Requires-Python: >=3.6
Provides-Extra: more_warnings
Provides-Extra: testing
